dd_pypi_test/__init__.py
dd_pypi_test-0.1.5.dist-info/METADATA
dd_pypi_test-0.1.5.dist-info/WHEEL
dd_pypi_test-0.1.5.dist-info/RECORD
