Metadata-Version: 2.1
Name: dd-pypi-test
Version: 0.1.5
Summary: My new project
Author: Bryce Thuilot
Author-email: bryce.thuilot@datadoghq.com
Requires-Python: >=3.8,<4.0
Classifier: Programming Language :: Python :: 3
Classifier: Programming Language :: Python :: 3.8
Classifier: Programming Language :: Python :: 3.9
Classifier: Programming Language :: Python :: 3.10
Classifier: Programming Language :: Python :: 3.11
Classifier: Programming Language :: Python :: 3.12
Classifier: Programming Language :: Python :: 3.13
Project-URL: repository, https://github.com/bthuilot/poutine.git
